{
  "stocks": [
    {"code": "000001", "name": "平安银行", "market": "SZ"},
    {"code": "000002", "name": "万科A", "market": "SZ"},
    {"code": "000063", "name": "中兴通讯", "market": "SZ"},
    {"code": "000333", "name": "美的集团", "market": "SZ"},
    {"code": "000338", "name": "潍柴动力", "market": "SZ"},
    {"code": "000425", "name": "徐工机械", "market": "SZ"},
    {"code": "000568", "name": "泸天化", "market": "SZ"},
    {"code": "000625", "name": "长安汽车", "market": "SZ"},
    {"code": "000651", "name": "格力电器", "market": "SZ"},
    {"code": "000725", "name": "京东方A", "market": "SZ"},
    {"code": "000768", "name": "中航西飞", "market": "SZ"},
    {"code": "000776", "name": "广发证券", "market": "SZ"},
    {"code": "000858", "name": "五粮液", "market": "SZ"},
    {"code": "000876", "name": "新希望", "market": "SZ"},
    {"code": "000938", "name": "紫光股份", "market": "SZ"},
    {"code": "001979", "name": "招商蛇口", "market": "SZ"},
    {"code": "002001", "name": "新和成", "market": "SZ"},
    {"code": "002007", "name": "华兰生物", "market": "SZ"},
    {"code": "002024", "name": "苏宁易购", "market": "SZ"},
    {"code": "002027", "name": "分众传媒", "market": "SZ"},
    {"code": "002049", "name": "紫光国微", "market": "SZ"},
    {"code": "002050", "name": "三花智控", "market": "SZ"},
    {"code": "002129", "name": "TCL中环", "market": "SZ"},
    {"code": "002142", "name": "宁波银行", "market": "SZ"},
    {"code": "002230", "name": "科大讯飞", "market": "SZ"},
    {"code": "002236", "name": "大华股份", "market": "SZ"},
    {"code": "002241", "name": "歌尔股份", "market": "SZ"},
    {"code": "002304", "name": "洋河股份", "market": "SZ"},
    {"code": "002311", "name": "海大集团", "market": "SZ"},
    {"code": "002352", "name": "顺丰控股", "market": "SZ"},
    {"code": "002410", "name": "广联达", "market": "SZ"},
    {"code": "002415", "name": "海康威视", "market": "SZ"},
    {"code": "002460", "name": "赣锋锂业", "market": "SZ"},
    {"code": "002475", "name": "立讯精密", "market": "SZ"},
    {"code": "002493", "name": "荣盛石化", "market": "SZ"},
    {"code": "002594", "name": "比亚迪", "market": "SZ"},
    {"code": "002601", "name": "龙蟒佰利", "market": "SZ"},
    {"code": "002603", "name": "以岭药业", "market": "SZ"},
    {"code": "002648", "name": "卫星化学", "market": "SZ"},
    {"code": "002714", "name": "牧原股份", "market": "SZ"},
    {"code": "300003", "name": "乐普医疗", "market": "SZ"},
    {"code": "300014", "name": "亿纬锂能", "market": "SZ"},
    {"code": "300015", "name": "爱尔眼科", "market": "SZ"},
    {"code": "300033", "name": "同花顺", "market": "SZ"},
    {"code": "300059", "name": "东方财富", "market": "SZ"},
    {"code": "300124", "name": "汇川技术", "market": "SZ"},
    {"code": "300142", "name": "沃森生物", "market": "SZ"},
    {"code": "300144", "name": "宋城演艺", "market": "SZ"},
    {"code": "300223", "name": "北京君正", "market": "SZ"},
    {"code": "300274", "name": "阳光电源", "market": "SZ"},
    {"code": "300327", "name": "中颖电子", "market": "SZ"},
    {"code": "300347", "name": "泰格医药", "market": "SZ"},
    {"code": "300408", "name": "三环集团", "market": "SZ"},
    {"code": "300413", "name": "芒果超媒", "market": "SZ"},
    {"code": "300433", "name": "蓝思科技", "market": "SZ"},
    {"code": "300450", "name": "先导智能", "market": "SZ"},
    {"code": "300454", "name": "深信服", "market": "SZ"},
    {"code": "300496", "name": "中科创达", "market": "SZ"},
    {"code": "300498", "name": "温氏股份", "market": "SZ"},
    {"code": "300529", "name": "健帆生物", "market": "SZ"},
    {"code": "300595", "name": "欧普康视", "market": "SZ"},
    {"code": "300628", "name": "亿联网络", "market": "SZ"},
    {"code": "300750", "name": "宁德时代", "market": "SZ"},
    {"code": "300760", "name": "迈瑞医疗", "market": "SZ"},
    {"code": "300782", "name": "卓胜微", "market": "SZ"},
    {"code": "600000", "name": "浦发银行", "market": "SH"},
    {"code": "600009", "name": "上海机场", "market": "SH"},
    {"code": "600010", "name": "包钢股份", "market": "SH"},
    {"code": "600011", "name": "华能国际", "market": "SH"},
    {"code": "600015", "name": "华夏银行", "market": "SH"},
    {"code": "600016", "name": "民生银行", "market": "SH"},
    {"code": "600018", "name": "上港集团", "market": "SH"},
    {"code": "600019", "name": "宝钢股份", "market": "SH"},
    {"code": "600025", "name": "华能水电", "market": "SH"},
    {"code": "600028", "name": "中国石化", "market": "SH"},
    {"code": "600029", "name": "南方航空", "market": "SH"},
    {"code": "600030", "name": "中信证券", "market": "SH"},
    {"code": "600031", "name": "三一重工", "market": "SH"},
    {"code": "600036", "name": "招商银行", "market": "SH"},
    {"code": "600048", "name": "保利发展", "market": "SH"},
    {"code": "600050", "name": "中国联通", "market": "SH"},
    {"code": "600066", "name": "宇通客车", "market": "SH"},
    {"code": "600085", "name": "同仁堂", "market": "SH"},
    {"code": "600089", "name": "特变电工", "market": "SH"},
    {"code": "600104", "name": "上汽集团", "market": "SH"},
    {"code": "600109", "name": "国金证券", "market": "SH"},
    {"code": "600111", "name": "北方稀土", "market": "SH"},
    {"code": "600132", "name": "重庆啤酒", "market": "SH"},
    {"code": "600150", "name": "中国船舶", "market": "SH"},
    {"code": "600183", "name": "生益科技", "market": "SH"},
    {"code": "600196", "name": "复星医药", "market": "SH"},
    {"code": "600219", "name": "南山铝业", "market": "SH"},
    {"code": "600233", "name": "圆通速递", "market": "SH"},
    {"code": "600276", "name": "恒瑞医药", "market": "SH"},
    {"code": "600309", "name": "万华化学", "market": "SH"},
    {"code": "600332", "name": "白云山", "market": "SH"},
    {"code": "600340", "name": "华夏幸福", "market": "SH"},
    {"code": "600346", "name": "恒力石化", "market": "SH"},
    {"code": "600352", "name": "浙江龙盛", "market": "SH"},
    {"code": "600383", "name": "金地集团", "market": "SH"},
    {"code": "600436", "name": "片仔癀", "market": "SH"},
    {"code": "600438", "name": "通威股份", "market": "SH"},
    {"code": "600486", "name": "扬农化工", "market": "SH"},
    {"code": "600489", "name": "中金黄金", "market": "SH"},
    {"code": "600519", "name": "贵州茅台", "market": "SH"},
    {"code": "600536", "name": "中国软件", "market": "SH"},
    {"code": "600547", "name": "山东黄金", "market": "SH"},
    {"code": "600570", "name": "恒生电子", "market": "SH"},
    {"code": "600588", "name": "用友网络", "market": "SH"},
    {"code": "600585", "name": "海螺水泥", "market": "SH"},
    {"code": "600590", "name": "五矿资本", "market": "SH"},
    {"code": "600596", "name": "新安股份", "market": "SH"},
    {"code": "600597", "name": "光明乳业", "market": "SH"},
    {"code": "600660", "name": "福耀玻璃", "market": "SH"},
    {"code": "600690", "name": "海尔智家", "market": "SH"},
    {"code": "600703", "name": "三安光电", "market": "SH"},
    {"code": "600745", "name": "闻泰科技", "market": "SH"},
    {"code": "600795", "name": "国电电力", "market": "SH"},
    {"code": "600809", "name": "山西汾酒", "market": "SH"},
    {"code": "600837", "name": "海通证券", "market": "SH"},
    {"code": "600845", "name": "宝信软件", "market": "SH"},
    {"code": "600848", "name": "上海临港", "market": "SH"},
    {"code": "600867", "name": "通化东宝", "market": "SH"},
    {"code": "600887", "name": "伊利股份", "market": "SH"},
    {"code": "600893", "name": "航发动力", "market": "SH"},
    {"code": "600900", "name": "长江电力", "market": "SH"},
    {"code": "600905", "name": "三峡能源", "market": "SH"},
    {"code": "600919", "name": "江苏银行", "market": "SH"},
    {"code": "600926", "name": "杭州银行", "market": "SH"},
    {"code": "600941", "name": "中国移动", "market": "SH"},
    {"code": "600958", "name": "东方证券", "market": "SH"},
    {"code": "600989", "name": "宝丰能源", "market": "SH"},
    {"code": "601012", "name": "隆基绿能", "market": "SH"},
    {"code": "601021", "name": "春秋航空", "market": "SH"},
    {"code": "601066", "name": "中信建投", "market": "SH"},
    {"code": "601088", "name": "中国神华", "market": "SH"},
    {"code": "601111", "name": "中国国航", "market": "SH"},
    {"code": "601138", "name": "工业富联", "market": "SH"},
    {"code": "601166", "name": "兴业银行", "market": "SH"},
    {"code": "601225", "name": "陕西煤业", "market": "SH"},
    {"code": "601238", "name": "广汽集团", "market": "SH"},
    {"code": "601288", "name": "农业银行", "market": "SH"},
    {"code": "601318", "name": "中国平安", "market": "SH"},
    {"code": "601319", "name": "中国人保", "market": "SH"},
    {"code": "601328", "name": "交通银行", "market": "SH"},
    {"code": "601336", "name": "新华保险", "market": "SH"},
    {"code": "601390", "name": "中国中铁", "market": "SH"},
    {"code": "601398", "name": "工商银行", "market": "SH"},
    {"code": "601601", "name": "中国太保", "market": "SH"},
    {"code": "601628", "name": "中国人寿", "market": "SH"},
    {"code": "601633", "name": "长城汽车", "market": "SH"},
    {"code": "601668", "name": "中国建筑", "market": "SH"},
    {"code": "601669", "name": "中国电建", "market": "SH"},
    {"code": "601688", "name": "华泰证券", "market": "SH"},
    {"code": "601728", "name": "中国电信", "market": "SH"},
    {"code": "601766", "name": "中国中车", "market": "SH"},
    {"code": "601788", "name": "光大证券", "market": "SH"},
    {"code": "601800", "name": "中国交建", "market": "SH"},
    {"code": "601816", "name": "京沪高铁", "market": "SH"},
    {"code": "601818", "name": "光大银行", "market": "SH"},
    {"code": "601857", "name": "中国石油", "market": "SH"},
    {"code": "601877", "name": "正泰电器", "market": "SH"},
    {"code": "601880", "name": "大连港", "market": "SH"},
    {"code": "601888", "name": "中国中免", "market": "SH"},
    {"code": "601899", "name": "紫金矿业", "market": "SH"},
    {"code": "601901", "name": "方正证券", "market": "SH"},
    {"code": "601919", "name": "中远海控", "market": "SH"},
    {"code": "601933", "name": "永辉超市", "market": "SH"},
    {"code": "601939", "name": "建设银行", "market": "SH"},
    {"code": "601988", "name": "中国银行", "market": "SH"},
    {"code": "601989", "name": "中国重工", "market": "SH"},
    {"code": "601995", "name": "中金公司", "market": "SH"},
    {"code": "601998", "name": "中信银行", "market": "SH"},
    {"code": "603160", "name": "汇顶科技", "market": "SH"},
    {"code": "601127", "name": "小康股份", "market": "SH"},
    {"code": "603259", "name": "药明康德", "market": "SH"},
    {"code": "603288", "name": "海天味业", "market": "SH"},
    {"code": "603501", "name": "韦尔股份", "market": "SH"},
    {"code": "603799", "name": "华友钴业", "market": "SH"},
    {"code": "603833", "name": "欧派家居", "market": "SH"},
    {"code": "603899", "name": "晨光股份", "market": "SH"},
    {"code": "603986", "name": "兆易创新", "market": "SH"},
    {"code": "605111", "name": "新洁能", "market": "SH"},
    {"code": "688008", "name": "澜起科技", "market": "SH"},
    {"code": "688012", "name": "中微公司", "market": "SH"},
    {"code": "688041", "name": "海光信息", "market": "SH"},
    {"code": "688065", "name": "凯盛新材", "market": "SH"},
    {"code": "688111", "name": "金山办公", "market": "SH"},
    {"code": "688126", "name": "沪硅产业", "market": "SH"},
    {"code": "688169", "name": "石头科技", "market": "SH"},
    {"code": "688187", "name": "时代电气", "market": "SH"},
    {"code": "688223", "name": "晶科能源", "market": "SH"},
    {"code": "688256", "name": "寒武纪", "market": "SH"},
    {"code": "688303", "name": "大全能源", "market": "SH"},
    {"code": "688363", "name": "华熙生物", "market": "SH"},
    {"code": "688396", "name": "华润微", "market": "SH"},
    {"code": "688567", "name": "孚能科技", "market": "SH"},
    {"code": "688599", "name": "天合光能", "market": "SH"},
    {"code": "688981", "name": "中芯国际", "market": "SH"}
  ]
}